vtreat/__init__.py
vtreat/cross_plan.py
vtreat/da_adapter.py
vtreat/effect_scaler.py
vtreat/partial_pooling_estimator.py
vtreat/stats_utils.py
vtreat/test_util.py
vtreat/transform.py
vtreat/util.py
vtreat/vtreat_api.py
vtreat/vtreat_db_adapter.py
vtreat/vtreat_impl.py
vtreat-1.3.1.dist-info/LICENSE
vtreat-1.3.1.dist-info/METADATA
vtreat-1.3.1.dist-info/WHEEL
vtreat-1.3.1.dist-info/top_level.txt
vtreat-1.3.1.dist-info/RECORD
