Metadata-Version: 2.1
Name: vtreat
Version: 1.3.1
Summary: vtreat is a pandas.DataFrame processor/conditioner that prepares real-world data for predictive modeling in a statistically sound manner. 
Home-page: https://github.com/WinVector/pyvtreat
Author: John Mount, Nina Zumel
Author-email: jmount@win-vector.com
License: License :: OSI Approved :: BSD 3-clause License
Platform: any
Classifier: Intended Audience :: Science/Research
Classifier: Programming Language :: Python
Classifier: Programming Language :: Python :: 3
Classifier: Programming Language :: Python :: 3.7
Classifier: Programming Language :: Python :: 3.8
Classifier: Programming Language :: Python :: 3.9
Classifier: Programming Language :: Python :: 3.10
Classifier: Programming Language :: Python :: 3.11
Classifier: License :: OSI Approved :: BSD License
Requires-Python: >=3.7
License-File: LICENSE
Requires-Dist: numpy <2,>=1.24.0
Requires-Dist: pandas <3,>=2.0.0
Requires-Dist: scipy <2,>=1.9.9
Requires-Dist: scikit-learn <2,>=1.0
Provides-Extra: all
Requires-Dist: data-algebra >=1.7.0 ; extra == 'all'
Provides-Extra: db_adapter
Requires-Dist: data-algebra >=1.7.0 ; extra == 'db_adapter'
